arm_rag/__init__.py
arm_rag/config/__init__.py
arm_rag/config/default_config.yaml
arm_rag/config/load_config.py
arm_rag/document_processing/__init__.py
arm_rag/document_processing/chunker.py
arm_rag/document_processing/parser.py
arm_rag/embeddings/__init__.py
arm_rag/embeddings/embedding.py
arm_rag/llm/__init__.py
arm_rag/llm/claude.py
arm_rag/llm/gpt.py
arm_rag/llm/model.py
arm_rag/llm/opensource.py
arm_rag/pipeline/__init__.py
arm_rag/pipeline/pipeline.py
arm_rag/vectorstore/__init__.py
arm_rag/vectorstore/deeplake_db.py
arm_rag/vectorstore/vector_db.py
arm_rag/vectorstore/weaviate_db.py
arm_rag_testing-7.7.9.dist-info/METADATA
arm_rag_testing-7.7.9.dist-info/WHEEL
arm_rag_testing-7.7.9.dist-info/top_level.txt
arm_rag_testing-7.7.9.dist-info/RECORD
