Metadata-Version: 2.1
Name: arm_rag_testing
Version: 7.7.9
Requires-Python: >=3.6
Requires-Dist: PyYAML ==6.0.2
Requires-Dist: python-docx ==1.1.2
Requires-Dist: Spire.Doc ==12.7.1
Requires-Dist: weaviate-client ==4.9.0
Requires-Dist: sentence-transformers ==3.2.1
Requires-Dist: python-dotenv ==1.0.1
Requires-Dist: tabulate ==0.9.0
Requires-Dist: python-multipart
Requires-Dist: anthropic ==0.37.1
Requires-Dist: openai ==1.52.2
Requires-Dist: deeplake ==3.9.26
Requires-Dist: pypdf ==5.1.0
Requires-Dist: gmft ==0.4.0
